nos_brick/__init__.py
nos_brick-0.0.1.dist-info/METADATA
nos_brick-0.0.1.dist-info/RECORD
nos_brick-0.0.1.dist-info/WHEEL
nos_brick-0.0.1.dist-info/top_level.txt
