Metadata-Version: 2.1
Name: nos-brick
Version: 0.0.1
Summary: Volume discovery and local storage management lib for non OpenStack deployments
Home-page: https://github.com/akrog/nos_brick
Author: Gorka Eguileor
Author-email: geguileo@redhat.com
License: Apache Software License 2.0
Keywords: nos_brick
Platform: UNKNOWN
Classifier: Development Status :: 2 - Pre-Alpha
Classifier: Intended Audience :: Developers
Classifier: License :: OSI Approved :: Apache Software License
Classifier: Natural Language :: English
Classifier: Programming Language :: Python :: 2
Classifier: Programming Language :: Python :: 2.6
Classifier: Programming Language :: Python :: 2.7
Classifier: Programming Language :: Python :: 3
Classifier: Programming Language :: Python :: 3.3
Classifier: Programming Language :: Python :: 3.4
Classifier: Programming Language :: Python :: 3.5
Requires-Dist: os-brick
